{
  "albums": [
    {
      "id": 1,
      "name": "In These Silent Days",
      "artist": "Brandi Carlile",
      "tracks" : [
        "Right on Time",
        "You and Me on the Rock (featuring Lucius)",
        "This Time Tomorrow",
        "Broken Horses",
        "Letter to the Past",
        "Mama Werewolf",
        "When You're Wrong",
        "Stay Gentle",
        "Sinners, Saints and Fools",
        "Throwing Good After Bad"
      ],
      "image": "https://upload.wikimedia.org/wikipedia/en/7/7a/Brandi_Carlile_-_In_These_Silent_Days.png",
      "rating": 8.5
    },
    {
      "id": 2,
      "name": "RENAISSANCE",
      "artist": "Beyoncé",
      "tracks" : [
        "I'M THAT GIRL",
        "COZY",
        "ALIEN SUPERSTAR",
        "CUFF IT",
        "ENERGY (featuring Beam)",
        "BREAK MY SOUL",
        "CHURCH GIRL",
        "PLASTIC OFF THE SOFA",
        "VIRGO'S GROOVE",
        "MOVE (featuring Grace Jones & Tems",
        "HEATED",
        "THIQUE",
        "ALL UP IN YOUR MIND",
        "AMERICA HAS A PROBLEM",
        "PURE/HONEY",
        "SUMMER RENAISSANCE"
      ],
      "image": "https://upload.wikimedia.org/wikipedia/en/a/ad/Beyonc%C3%A9_-_Renaissance.png",
      "rating": 8.7
    },
    {
      "id": 3,
      "name": "30",
      "artist": "Adele",
      "tracks" : [
        "Strangers By Nature",
        "Easy On Me",
        "My Little Love",
        "Cry Your Heart Out",
        "Oh My God",
        "Can I Get It",
        "I Drink Wine",
        "All Night Parking (with Erroll Garner) Interlude",
        "Woman Like Me",
        "Hold On",
        "To Be Loved",
        "Love Is A Game"
      ],
      "image": "https://assets.vogue.com/photos/6193ef9136fdadae89a07fe9/1:1/w_3000,h_3000,c_limit/COVER_no-text_10X10_RGB.jpg",
      "rating": 8.8
    }
  ]
}
